django_lang_switch/__init__.py
django_lang_switch/apps.py
django_lang_switch/urls.py
django_lang_switch/static/django_lang_switch/css/lang_switch.css
django_lang_switch/static/django_lang_switch/js/lang_switch.js
django_lang_switch/templates/admin/base_site.html
django_lang_switch/templates/django_lang_switch/dropdown.html
django_lang_switch/templatetags/__init__.py
django_lang_switch/templatetags/lang_switch.py
django_lang_switch/tests/__init__.py
django_lang_switch/tests/settings.py
django_lang_switch/tests/test_templatetags.py
django_lang_switch/tests/urls.py
django_lang_switch-0.3.dist-info/DESCRIPTION.rst
django_lang_switch-0.3.dist-info/METADATA
django_lang_switch-0.3.dist-info/RECORD
django_lang_switch-0.3.dist-info/WHEEL
django_lang_switch-0.3.dist-info/metadata.json
django_lang_switch-0.3.dist-info/top_level.txt
