Metadata-Version: 2.0
Name: django-lang-switch
Version: 0.3
Summary: Language switch for Django
Home-page: https://github.com/stinovlas/django-lang-switch
Author: Jan Musílek
Author-email: jan.musilek@nic.cz
License: UNKNOWN
Platform: UNKNOWN
Classifier: Development Status :: 2 - Pre-Alpha
Classifier: Environment :: Web Environment
Classifier: Framework :: Django
Classifier: Framework :: Django :: 2.0
Classifier: Framework :: Django :: 2.1
Classifier: Intended Audience :: Developers
Classifier: License :: OSI Approved :: GNU General Public License v3 (GPLv3)
Classifier: Operating System :: OS Independent
Classifier: Programming Language :: Python
Classifier: Programming Language :: Python :: 3.5
Classifier: Programming Language :: Python :: 3.6
Classifier: Programming Language :: Python :: 3.7
Classifier: Topic :: Internet :: WWW/HTTP
Classifier: Topic :: Internet :: WWW/HTTP :: Dynamic Content
Requires-Python: >=3.5
Provides-Extra: quality
Requires-Dist: Django (>=2.0)
Provides-Extra: quality
Requires-Dist: flake8; extra == 'quality'
Requires-Dist: isort; extra == 'quality'
Requires-Dist: mypy; extra == 'quality'
Requires-Dist: pydocstyle; extra == 'quality'
